excel_ngrams/__init__.py
excel_ngrams/console.py
excel_ngrams/grammer.py
excel_ngrams-0.2.0.dist-info/entry_points.txt
excel_ngrams-0.2.0.dist-info/LICENSE
excel_ngrams-0.2.0.dist-info/WHEEL
excel_ngrams-0.2.0.dist-info/METADATA
excel_ngrams-0.2.0.dist-info/RECORD
